hololinked/__init__.py
hololinked/config.py
hololinked/constants.py
hololinked/logger.py
hololinked/utils.py
hololinked/client/__init__.py
hololinked/client/abstractions.py
hololinked/client/exceptions.py
hololinked/client/factory.py
hololinked/client/proxy.py
hololinked/client/security.py
hololinked/client/http/__init__.py
hololinked/client/http/consumed_interactions.py
hololinked/client/mqtt/__init__.py
hololinked/client/mqtt/consumed_interactions.py
hololinked/client/zmq/__init__.py
hololinked/client/zmq/consumed_interactions.py
hololinked/core/__init__.py
hololinked/core/actions.py
hololinked/core/dataklasses.py
hololinked/core/events.py
hololinked/core/exceptions.py
hololinked/core/logger.py
hololinked/core/meta.py
hololinked/core/properties.py
hololinked/core/property.py
hololinked/core/state_machine.py
hololinked/core/thing.py
hololinked/core/zmq/__init__.py
hololinked/core/zmq/brokers.py
hololinked/core/zmq/message.py
hololinked/core/zmq/rpc_server.py
hololinked/param/__init__.py
hololinked/param/exceptions.py
hololinked/param/extensions.py
hololinked/param/ipython.py
hololinked/param/logger.py
hololinked/param/parameterized.py
hololinked/param/parameters.py
hololinked/param/serializer.py
hololinked/param/utils.py
hololinked/schema_validators/__init__.py
hololinked/schema_validators/json_schema.py
hololinked/schema_validators/validators.py
hololinked/serializers/__init__.py
hololinked/serializers/payloads.py
hololinked/serializers/serializers.py
hololinked/server/__init__.py
hololinked/server/repository.py
hololinked/server/security.py
hololinked/server/server.py
hololinked/server/http/__init__.py
hololinked/server/http/config.py
hololinked/server/http/controllers.py
hololinked/server/http/server.py
hololinked/server/http/services.py
hololinked/server/mqtt/__init__.py
hololinked/server/mqtt/config.py
hololinked/server/mqtt/controllers.py
hololinked/server/mqtt/server.py
hololinked/server/mqtt/services.py
hololinked/server/zmq/__init__.py
hololinked-0.3.10.dist-info/licenses/license.txt
hololinked-0.3.10.dist-info/licenses/licenses/labthings-fastapi-LICENSE.txt
hololinked-0.3.10.dist-info/licenses/licenses/param-LICENSE.txt
hololinked-0.3.10.dist-info/licenses/licenses/pyro-LICENSE.txt
hololinked-0.3.10.dist-info/licenses/licenses/wotpy-LICENSE.txt
hololinked-0.3.10.dist-info/METADATA
hololinked-0.3.10.dist-info/WHEEL
hololinked-0.3.10.dist-info/top_level.txt
hololinked-0.3.10.dist-info/RECORD
