Metadata-Version: 2.4
Name: hololinked
Version: 0.3.10
Summary: A ZMQ-based protocol-agnostic object oriented RPC toolkit primarily focussed for instrumentation control, data acquisition or IoT
Author-email: Vignesh Vaidyanathan <info@hololinked.dev>
License-Expression: Apache-2.0
Project-URL: Documentation, https://docs.hololinked.dev
Project-URL: Repository, https://github.com/hololinked-dev/hololinked
Keywords: data-acquisition,zmq-rpc,SCADA,IoT,Web of Things,remote data logging
Classifier: Programming Language :: Python :: 3
Classifier: Operating System :: OS Independent
Classifier: Intended Audience :: Information Technology
Classifier: Intended Audience :: Science/Research
Classifier: Intended Audience :: Healthcare Industry
Classifier: Intended Audience :: Manufacturing
Classifier: Intended Audience :: Developers
Classifier: Intended Audience :: End Users/Desktop
Classifier: Intended Audience :: Education
Classifier: Topic :: Internet :: WWW/HTTP
Classifier: Topic :: Internet :: WWW/HTTP :: Browsers
Classifier: Topic :: Scientific/Engineering :: Human Machine Interfaces
Classifier: Topic :: System :: Hardware
Classifier: Development Status :: 4 - Beta
Requires-Python: >=3.11
License-File: licenses/labthings-fastapi-LICENSE.txt
License-File: licenses/param-LICENSE.txt
License-File: licenses/pyro-LICENSE.txt
License-File: licenses/wotpy-LICENSE.txt
License-File: license.txt
Requires-Dist: msgspec>=0.18.6
Requires-Dist: pyzmq<26.2,>=25.1.0
Requires-Dist: pydantic<3.0.0,>=2.8.0
Requires-Dist: tornado>=6.3.3
Requires-Dist: jsonschema<5.0,>=4.22.0
Requires-Dist: httpx<29.0,>=0.28.1
Requires-Dist: sniffio<2.0,>=1.3.1
Requires-Dist: aiomqtt>=2.4.0
Requires-Dist: structlog>=25.5.0
Requires-Dist: ifaddr<0.3,>=0.2.0
Requires-Dist: fastjsonschema==2.20.0
Requires-Dist: serpent<2.0,>=1.41
Requires-Dist: bcrypt==4.3.0
Requires-Dist: argon2-cffi>=23.1.0
Requires-Dist: sqlalchemy>2.0.21
Requires-Dist: sqlalchemy-utils>=0.41
Requires-Dist: psycopg2-binary>=2.9.11
Requires-Dist: pymongo>=4.15.2
Dynamic: license-file
